GeN/GeN.py
GeN/__init__.py
gen_optim-0.1.1.dist-info/licenses/LICENSE
gen_optim-0.1.1.dist-info/METADATA
gen_optim-0.1.1.dist-info/WHEEL
gen_optim-0.1.1.dist-info/top_level.txt
gen_optim-0.1.1.dist-info/RECORD
