Metadata-Version: 2.4
Name: gen-optim
Version: 0.1.1
Summary: Pytorch implementation of Generalized Newton's method (GeN), a learning-rate-free and Hessian-informed optimization.
Home-page: https://github.com/ShiyunXu/gen-optim
Author: Zhiqi Bu, Shiyun Xu
Author-email: shiyunxulara@gmail.com
Classifier: Programming Language :: Python :: 3
Classifier: License :: OSI Approved :: MIT License
Classifier: Operating System :: OS Independent
Requires-Python: >=3.8
License-File: LICENSE
Dynamic: author
Dynamic: author-email
Dynamic: classifier
Dynamic: description
Dynamic: description-content-type
Dynamic: home-page
Dynamic: license-file
Dynamic: requires-python
Dynamic: summary
